bloodhound_import/__init__.py
bloodhound_import/__main__.py
bloodhound_import/database.py
bloodhound_import/importer.py
bloodhound_import-0.0.3.dist-info/DESCRIPTION.rst
bloodhound_import-0.0.3.dist-info/METADATA
bloodhound_import-0.0.3.dist-info/RECORD
bloodhound_import-0.0.3.dist-info/WHEEL
bloodhound_import-0.0.3.dist-info/entry_points.txt
bloodhound_import-0.0.3.dist-info/metadata.json
bloodhound_import-0.0.3.dist-info/top_level.txt
